keras_mixnets/__init__.py
keras_mixnets/config.py
keras_mixnets/custom_objects.py
keras_mixnets/mixnets.py
keras_mixnets/temp.py
keras_mixnets-0.1.0.dist-info/LICENSE
keras_mixnets-0.1.0.dist-info/METADATA
keras_mixnets-0.1.0.dist-info/WHEEL
keras_mixnets-0.1.0.dist-info/top_level.txt
keras_mixnets-0.1.0.dist-info/RECORD
