Metadata-Version: 2.1
Name: keras-mixnets
Version: 0.1.0
Summary: Keras implementation of MixNets of any configuration.
Home-page: https://github.com/titu1994/keras_mixnets
Author: Somshubra Majumdar
Author-email: titu1994@gmail.com
License: MIT
Download-URL: https://github.com/titu1994/keras_mixnets
Platform: UNKNOWN
Classifier: Programming Language :: Python :: 3
Classifier: Programming Language :: Python :: 3.5
Classifier: Programming Language :: Python :: 3.6
Classifier: Programming Language :: Python :: 3.7
Classifier: License :: OSI Approved :: MIT License
Classifier: Operating System :: OS Independent
Classifier: Topic :: Software Development :: Libraries
Classifier: Topic :: Software Development :: Libraries :: Python Modules
Requires-Python: >=3.0.0
Requires-Dist: keras (>=2.2.4)
Requires-Dist: scipy (>=1.1.0)
Requires-Dist: scikit-learn (>=0.21.2)
Provides-Extra: test
Requires-Dist: pytest; extra == 'test'
Requires-Dist: pillow; extra == 'test'
